dylog/__init__.py
dylog/handlers.py
dylog-0.0.8.dist-info/LICENSE
dylog-0.0.8.dist-info/LICENSE.md
dylog-0.0.8.dist-info/METADATA
dylog-0.0.8.dist-info/WHEEL
dylog-0.0.8.dist-info/top_level.txt
dylog-0.0.8.dist-info/RECORD
